setup.cfg
setup.py
sentry_kafka/__init__.py
sentry_kafka/models.py
sentry_kafka.egg-info/PKG-INFO
sentry_kafka.egg-info/SOURCES.txt
sentry_kafka.egg-info/dependency_links.txt
sentry_kafka.egg-info/entry_points.txt
sentry_kafka.egg-info/not-zip-safe
sentry_kafka.egg-info/pbr.json
sentry_kafka.egg-info/requires.txt
sentry_kafka.egg-info/top_level.txt